jjpbaje/__init__.py
jjpbaje/jjpbaje.py
jjpbaaje-0.0.1.dist-info/METADATA
jjpbaaje-0.0.1.dist-info/WHEEL
jjpbaaje-0.0.1.dist-info/top_level.txt
jjpbaaje-0.0.1.dist-info/RECORD
