Metadata-Version: 2.1
Name: jjpbaaje
Version: 0.0.1
Summary: simple one
Author: R Sai Praneeth
Author-email: praneeth.renduchinthala210@gmail.com
Classifier: Programming Language :: Python :: 3
Classifier: License :: OSI Approved :: MIT License
Classifier: Operating System :: OS Independent
Requires-Python: >=3.7
